core/__init__.py
core/main.py
ddsinpy-0.0.3.dist-info/LICENSE
ddsinpy-0.0.3.dist-info/METADATA
ddsinpy-0.0.3.dist-info/WHEEL
ddsinpy-0.0.3.dist-info/top_level.txt
ddsinpy-0.0.3.dist-info/RECORD
