Metadata-Version: 2.1
Name: ddsinpy
Version: 0.0.3
Summary: Robust Dynamic Data Structures in Python
Home-page: https://github.com/walidbou6/ddspy
Author: Bousseta Walid
Author-email: wali.bousseta@gmail.com
License: UNKNOWN
Project-URL: Bug Tracker, https://github.com/walidbou6/ddspy/issues
Platform: UNKNOWN
Classifier: Programming Language :: Python :: 3
Classifier: License :: OSI Approved :: MIT License
Classifier: Operating System :: OS Independent
Requires-Python: >=3.6
License-File: LICENSE
